konnected/__init__.py
konnected-1.2.0.dist-info/LICENSE.txt
konnected-1.2.0.dist-info/METADATA
konnected-1.2.0.dist-info/WHEEL
konnected-1.2.0.dist-info/top_level.txt
konnected-1.2.0.dist-info/RECORD
