Metadata-Version: 2.1
Name: konnected
Version: 1.2.0
Summary: An async Python library for interacting with Konnected home automation controllers (see https://konnected.io)
Home-page: https://github.com/konnected-io/konnected-py
Author: Nate Clark, Konnected Inc
Author-email: help@konnected.io
License: MIT
Project-URL: Homepage, https://github.com/konnected-io/konnected-py
Project-URL: Website & Online Store, https://konnected.io
Project-URL: Support and Community Forums, https://help.konnected.io
Project-URL: Facebook, https://facebook.com/konnected.io
Project-URL: YouTube Channel, https://youtube.com/c/Konnected
Platform: UNKNOWN
Classifier: Intended Audience :: Developers
Classifier: Operating System :: OS Independent
Classifier: Programming Language :: Python
Classifier: Programming Language :: Python :: 3
Classifier: Topic :: Software Development :: Libraries :: Python Modules
Classifier: License :: OSI Approved :: MIT License
Requires-Dist: aiohttp (>=3.6.1)
